{
 "entities": {
  "FcL9bbjwdUrgjVT_0": {
   "reference_plane": {},
   "type": "Sketch",
   "name": "Sketch 1",
   "profiles": {
    "JGS": {
     "loops": [
      {
       "profile_curves": [
        {
         "center_point": {
          "y": 0.0,
          "x": -0.06,
          "z": 0.0
         },
         "start_angle": 0.0,
         "radius": 0.003,
         "end_point": {
          "y": 0.00146741,
          "x": -0.05738338,
          "z": 0.0
         },
         "start_point": {
          "y": 0.00259808,
          "x": -0.0615,
          "z": 0.0
         },
         "normal": {
          "y": 0.0,
          "x": 0.0,
          "z": 1.0
         },
         "type": "Arc3D",
         "curve": "JGV",
         "end_angle": 4.6998907269923365,
         "reference_vector": {
          "y": 0.8660257195044776,
          "x": -0.499999453156453,
          "z": 0.0
         }
        },
        {
         "center_point": {
          "y": -0.10392305,
          "x": 0.0,
          "z": 0.0
         },
         "start_angle": 0.0,
         "radius": 0.12,
         "end_point": {
          "y": 0.00146741,
          "x": -0.05738338,
          "z": 0.0
         },
         "start_point": {
          "y": 0.01606758,
          "x": -0.0015,
          "z": 0.0
         },
         "normal": {
          "y": 0.0,
          "x": 0.0,
          "z": 1.0
         },
         "type": "Arc3D",
         "curve": "JGJ",
         "end_angle": 0.48609780446462114,
         "reference_vector": {
          "y": 0.999921871954991,
          "x": -0.012499999441060412,
          "z": 0.0
         }
        },
        {
         "start_point": {
          "y": 0.01756758,
          "x": -0.0015,
          "z": 0.0
         },
         "type": "Line3D",
         "curve": "JGN",
         "end_point": {
          "y": 0.01606758,
          "x": -0.0015,
          "z": 0.0
         }
        },
        {
         "start_point": {
          "y": 0.01756758,
          "x": -0.0015,
          "z": 0.0
         },
         "type": "Line3D",
         "curve": "JGF",
         "end_point": {
          "y": 0.01756758,
          "x": 0.0,
          "z": 0.0
         }
        },
        {
         "start_point": {
          "y": 0.01756758,
          "x": 0.0,
          "z": 0.0
         },
         "type": "Line3D",
         "curve": "JGp",
         "end_point": {
          "y": 0.01756758,
          "x": 0.0015,
          "z": 0.0
         }
        },
        {
         "start_point": {
          "y": 0.01606758,
          "x": 0.0015,
          "z": 0.0
         },
         "type": "Line3D",
         "curve": "JGt",
         "end_point": {
          "y": 0.01756758,
          "x": 0.0015,
          "z": 0.0
         }
        },
        {
         "center_point": {
          "y": -0.10392305,
          "x": 0.0,
          "z": 0.0
         },
         "start_angle": 0.0,
         "radius": 0.12,
         "end_point": {
          "y": 0.01606758,
          "x": 0.0015,
          "z": 0.0
         },
         "start_point": {
          "y": 0.00146741,
          "x": 0.05738338,
          "z": 0.0
         },
         "normal": {
          "y": 0.0,
          "x": 0.0,
          "z": -1.0
         },
         "type": "Arc3D",
         "curve": "JGl",
         "end_angle": 0.48609780446462114,
         "reference_vector": {
          "y": 0.8782537918835367,
          "x": 0.47819481076459763,
          "z": 0.0
         }
        },
        {
         "center_point": {
          "y": 0.0,
          "x": 0.06,
          "z": 0.0
         },
         "start_angle": 0.0,
         "radius": 0.003,
         "end_point": {
          "y": 0.00146741,
          "x": 0.05738338,
          "z": 0.0
         },
         "start_point": {
          "y": 0.00259808,
          "x": 0.0615,
          "z": 0.0
         },
         "normal": {
          "y": 0.0,
          "x": 0.0,
          "z": -1.0
         },
         "type": "Arc3D",
         "curve": "JGd",
         "end_angle": 4.6998907269923365,
         "reference_vector": {
          "y": 0.4891368750254326,
          "x": -0.8722070382027162,
          "z": 0.0
         }
        },
        {
         "center_point": {
          "y": -0.10392305,
          "x": 0.0,
          "z": 0.0
         },
         "radius": 0.123,
         "normal": {
          "y": 0.0,
          "x": 0.0,
          "z": 1.0
         },
         "curve": "JGB+JGh",
         "start_angle": 0.0,
         "end_angle": 1.0471975078265663,
         "type": "Arc3D",
         "start_point": {
          "x": 0.061499997690087724,
          "y": 0.00259807599911438,
          "z": 0.0
         },
         "end_point": {
          "x": -0.061499997690087724,
          "y": 0.0025980759991143937,
          "z": 0.0
         },
         "reference_vector": {
          "x": 0.49999998122022543,
          "y": 0.8660254146269463,
          "z": 0.0
         }
        }
       ],
       "is_outer": true
      },
      {
       "profile_curves": [
        {
         "center_point": {
          "y": 0.0,
          "x": -0.06,
          "z": 0.0
         },
         "radius": 0.001,
         "type": "Circle3D",
         "curve": "JGR",
         "normal": {
          "y": 0.0,
          "x": 0.0,
          "z": 1.0
         }
        }
       ],
       "is_outer": true
      },
      {
       "profile_curves": [
        {
         "center_point": {
          "y": 0.0,
          "x": 0.06,
          "z": 0.0
         },
         "radius": 0.001,
         "type": "Circle3D",
         "curve": "JGZ",
         "normal": {
          "y": 0.0,
          "x": 0.0,
          "z": -1.0
         }
        }
       ],
       "is_outer": true
      }
     ],
     "properties": {}
    },
    "JGK": {
     "loops": [
      {
       "profile_curves": [
        {
         "center_point": {
          "y": -0.02536398,
          "x": -0.06004514,
          "z": 0.0
         },
         "radius": 0.001,
         "type": "Circle3D",
         "curve": "JG9",
         "normal": {
          "y": 0.0,
          "x": 0.0,
          "z": 1.0
         }
        }
       ],
       "is_outer": true
      }
     ],
     "properties": {}
    },
    "JGO": {
     "loops": [
      {
       "profile_curves": [
        {
         "center_point": {
          "y": -0.02536398,
          "x": 0.05991566,
          "z": 0.0
         },
         "radius": 0.001,
         "type": "Circle3D",
         "curve": "KGFB",
         "normal": {
          "y": 0.0,
          "x": 0.0,
          "z": -1.0
         }
        }
       ],
       "is_outer": true
      }
     ],
     "properties": {}
    },
    "JGC": {
     "loops": [
      {
       "profile_curves": [
        {
         "center_point": {
          "y": 0.0,
          "x": -0.06,
          "z": 0.0
         },
         "radius": 0.001,
         "type": "Circle3D",
         "curve": "JGR",
         "normal": {
          "y": 0.0,
          "x": 0.0,
          "z": 1.0
         }
        }
       ],
       "is_outer": true
      }
     ],
     "properties": {}
    },
    "JGW": {
     "loops": [
      {
       "profile_curves": [
        {
         "center_point": {
          "y": -0.12928703,
          "x": -4.514e-05,
          "z": 0.0
         },
         "start_angle": 0.0,
         "radius": 0.123,
         "end_point": {
          "y": -0.0227659,
          "x": -0.06154514,
          "z": 0.0
         },
         "start_point": {
          "y": -0.00629641,
          "x": -0.00156474,
          "z": 0.0
         },
         "normal": {
          "y": 0.0,
          "x": 0.0,
          "z": 1.0
         },
         "type": "Arc3D",
         "curve": "JGx",
         "end_angle": 0.511243968795503,
         "reference_vector": {
          "y": 0.9999236806131413,
          "x": -0.012354470812975247,
          "z": 0.0
         }
        },
        {
         "center_point": {
          "y": -0.02536398,
          "x": -0.06004514,
          "z": 0.0
         },
         "start_angle": 0.0,
         "radius": 0.003,
         "end_point": {
          "y": -0.02389657,
          "x": -0.05742852,
          "z": 0.0
         },
         "start_point": {
          "y": -0.0227659,
          "x": -0.06154514,
          "z": 0.0
         },
         "normal": {
          "y": 0.0,
          "x": 0.0,
          "z": 1.0
         },
         "type": "Arc3D",
         "curve": "KGBB",
         "end_angle": 4.699890726992338,
         "reference_vector": {
          "y": 0.8660257195044778,
          "x": -0.49999945315645267,
          "z": 0.0
         }
        },
        {
         "center_point": {
          "y": -0.12928679,
          "x": -4.47e-05,
          "z": 0.0
         },
         "start_angle": 0.0,
         "radius": 0.12,
         "end_point": {
          "y": -0.02389657,
          "x": -0.05742852,
          "z": 0.0
         },
         "start_point": {
          "y": -0.00929641,
          "x": -0.00156474,
          "z": 0.0
         },
         "normal": {
          "y": 0.0,
          "x": 0.0,
          "z": 1.0
         },
         "type": "Arc3D",
         "curve": "JG5",
         "end_angle": 0.48593496813341885,
         "reference_vector": {
          "y": 0.9999197703472085,
          "x": -0.01266699920209079,
          "z": 0.0
         }
        },
        {
         "start_point": {
          "y": -0.00929641,
          "x": -0.00156474,
          "z": 0.0
         },
         "type": "Line3D",
         "curve": "KGdB",
         "end_point": {
          "y": -0.00929641,
          "x": 0.00143526,
          "z": 0.0
         }
        },
        {
         "center_point": {
          "y": -0.12928679,
          "x": -8.478e-05,
          "z": 0.0
         },
         "start_angle": 0.0,
         "radius": 0.12,
         "end_point": {
          "y": -0.00929641,
          "x": 0.00143526,
          "z": 0.0
         },
         "start_point": {
          "y": -0.02389657,
          "x": 0.05729904,
          "z": 0.0
         },
         "normal": {
          "y": 0.0,
          "x": 0.0,
          "z": -1.0
         },
         "type": "Arc3D",
         "curve": "KGNB",
         "end_angle": 0.48593496813341885,
         "reference_vector": {
          "y": 0.8782517946219224,
          "x": 0.47819847892206085,
          "z": 0.0
         }
        },
        {
         "center_point": {
          "y": -0.02536398,
          "x": 0.05991566,
          "z": 0.0
         },
         "start_angle": 0.0,
         "radius": 0.003,
         "end_point": {
          "y": -0.02389657,
          "x": 0.05729904,
          "z": 0.0
         },
         "start_point": {
          "y": -0.0227659,
          "x": 0.06141566,
          "z": 0.0
         },
         "normal": {
          "y": 0.0,
          "x": 0.0,
          "z": -1.0
         },
         "type": "Arc3D",
         "curve": "KGJB",
         "end_angle": 4.69989072699234,
         "reference_vector": {
          "y": 0.48913687502543324,
          "x": -0.8722070382027157,
          "z": 0.0
         }
        },
        {
         "center_point": {
          "y": -0.12928703,
          "x": -8.434e-05,
          "z": 0.0
         },
         "start_angle": 0.0,
         "radius": 0.123,
         "end_point": {
          "y": -0.00629641,
          "x": 0.00143526,
          "z": 0.0
         },
         "start_point": {
          "y": -0.0227659,
          "x": 0.06141566,
          "z": 0.0
         },
         "normal": {
          "y": 0.0,
          "x": 0.0,
          "z": -1.0
         },
         "type": "Arc3D",
         "curve": "KGhB",
         "end_angle": 0.511243968795503,
         "reference_vector": {
          "y": 0.8660254146269463,
          "x": 0.4999999812202255,
          "z": 0.0
         }
        },
        {
         "start_point": {
          "y": -0.00779641,
          "x": 0.00143526,
          "z": 0.0
         },
         "type": "Line3D",
         "curve": "KGZB",
         "end_point": {
          "y": -0.00629641,
          "x": 0.00143526,
          "z": 0.0
         }
        },
        {
         "start_point": {
          "y": -0.00779641,
          "x": -6.474e-05,
          "z": 0.0
         },
         "type": "Line3D",
         "curve": "KGRB",
         "end_point": {
          "y": -0.00779641,
          "x": 0.00143526,
          "z": 0.0
         }
        },
        {
         "start_point": {
          "y": -0.00779641,
          "x": -0.00156474,
          "z": 0.0
         },
         "type": "Line3D",
         "curve": "JG1",
         "end_point": {
          "y": -0.00779641,
          "x": -6.474e-05,
          "z": 0.0
         }
        },
        {
         "start_point": {
          "y": -0.00629641,
          "x": -0.00156474,
          "z": 0.0
         },
         "type": "Line3D",
         "curve": "KGVB",
         "end_point": {
          "y": -0.00779641,
          "x": -0.00156474,
          "z": 0.0
         }
        }
       ],
       "is_outer": true
      },
      {
       "profile_curves": [
        {
         "center_point": {
          "y": -0.02536398,
          "x": -0.06004514,
          "z": 0.0
         },
         "radius": 0.001,
         "type": "Circle3D",
         "curve": "JG9",
         "normal": {
          "y": 0.0,
          "x": 0.0,
          "z": 1.0
         }
        }
       ],
       "is_outer": true
      },
      {
       "profile_curves": [
        {
         "center_point": {
          "y": -0.02536398,
          "x": 0.05991566,
          "z": 0.0
         },
         "radius": 0.001,
         "type": "Circle3D",
         "curve": "KGFB",
         "normal": {
          "y": 0.0,
          "x": 0.0,
          "z": -1.0
         }
        }
       ],
       "is_outer": true
      }
     ],
     "properties": {}
    },
    "JGG": {
     "loops": [
      {
       "profile_curves": [
        {
         "center_point": {
          "y": 0.0,
          "x": 0.06,
          "z": 0.0
         },
         "radius": 0.001,
         "type": "Circle3D",
         "curve": "JGZ",
         "normal": {
          "y": 0.0,
          "x": 0.0,
          "z": -1.0
         }
        }
       ],
       "is_outer": true
      }
     ],
     "properties": {}
    }
   },
   "transform": {
    "origin": {
     "y": 0.0,
     "x": 0.0,
     "z": 0.0
    },
    "y_axis": {
     "y": 1.0,
     "x": 0.0,
     "z": 0.0
    },
    "x_axis": {
     "y": 0.0,
     "x": 1.0,
     "z": 0.0
    },
    "z_axis": {
     "y": 0.0,
     "x": 0.0,
     "z": 1.0
    }
   }
  },
  "FPaoPE5FpGRsXmf_0": {
   "extent_two": {
    "distance": {
     "role": "AgainstDistance",
     "type": "ModelParameter",
     "name": "none",
     "value": 0.0
    },
    "type": "DistanceExtentDefinition",
    "taper_angle": {
     "role": "Side2TaperAngle",
     "type": "ModelParameter",
     "name": "none",
     "value": 0.0
    }
   },
   "name": "Extrude 1",
   "extent_one": {
    "distance": {
     "role": "AlongDistance",
     "type": "ModelParameter",
     "name": "none",
     "value": 0.003
    },
    "type": "DistanceExtentDefinition",
    "taper_angle": {
     "role": "TaperAngle",
     "type": "ModelParameter",
     "name": "none",
     "value": 0.0
    }
   },
   "extent_type": "OneSideFeatureExtentType",
   "operation": "NewBodyFeatureOperation",
   "start_extent": {
    "type": "ProfilePlaneStartDefinition"
   },
   "type": "ExtrudeFeature",
   "profiles": [
    {
     "profile": "JGS",
     "sketch": "FcL9bbjwdUrgjVT_0"
    },
    {
     "profile": "JGW",
     "sketch": "FcL9bbjwdUrgjVT_0"
    }
   ]
  }
 },
 "properties": {
  "bounding_box": {
   "max_point": {
    "y": 0.019076951545867346,
    "x": 0.06299999999999999,
    "z": 0.003
   },
   "type": "BoundingBox3D",
   "min_point": {
    "y": -0.028363979161449934,
    "x": -0.06304514403167705,
    "z": 0.0
   }
  }
 },
 "sequence": [
  {
   "index": 0,
   "type": "Sketch",
   "entity": "FcL9bbjwdUrgjVT_0"
  },
  {
   "index": 1,
   "type": "ExtrudeFeature",
   "entity": "FPaoPE5FpGRsXmf_0"
  }
 ]
}