{
 "entities": {
  "FQPC0yPl8ZFWFSQ_0": {
   "reference_plane": {}, 
   "type": "Sketch", 
   "name": "Top L2", 
   "profiles": {
    "KGqB": {
     "loops": [
      {
       "profile_curves": [
        {
         "center_point": {
          "y": 0.0283582, 
          "x": -0.10487832, 
          "z": 0.0
         }, 
         "radius": 0.00065, 
         "type": "Circle3D", 
         "curve": "KGJG", 
         "normal": {
          "y": 0.0, 
          "x": 0.0, 
          "z": 1.0
         }
        }
       ], 
       "is_outer": true
      }
     ], 
     "properties": {}
    }, 
    "JGK": {
     "loops": [
      {
       "profile_curves": [
        {
         "center_point": {
          "y": 0.0283582, 
          "x": 0.08546928, 
          "z": 0.0
         }, 
         "radius": 0.00065, 
         "type": "Circle3D", 
         "curve": "JGl", 
         "normal": {
          "y": 0.0, 
          "x": 0.0, 
          "z": 1.0
         }
        }
       ], 
       "is_outer": true
      }
     ], 
     "properties": {}
    }, 
    "JGO": {
     "loops": [
      {
       "profile_curves": [
        {
         "center_point": {
          "y": 0.0283582, 
          "x": 0.08300928, 
          "z": 0.0
         }, 
         "radius": 0.00065, 
         "type": "Circle3D", 
         "curve": "JGp", 
         "normal": {
          "y": 0.0, 
          "x": 0.0, 
          "z": 1.0
         }
        }
       ], 
       "is_outer": true
      }
     ], 
     "properties": {}
    }, 
    "JGC": {
     "loops": [
      {
       "profile_curves": [
        {
         "start_point": {
          "y": -0.0251418, 
          "x": 0.12406074, 
          "z": 0.0
         }, 
         "type": "Line3D", 
         "curve": "JGB", 
         "end_point": {
          "y": 0.0138582, 
          "x": 0.12406074, 
          "z": 0.0
         }
        }, 
        {
         "start_point": {
          "y": 0.0138582, 
          "x": 0.12406074, 
          "z": 0.0
         }, 
         "type": "Line3D", 
         "curve": "JGN", 
         "end_point": {
          "y": 0.0138582, 
          "x": 0.12031074, 
          "z": 0.0
         }
        }, 
        {
         "start_point": {
          "y": 0.0138582, 
          "x": 0.12031074, 
          "z": 0.0
         }, 
         "type": "Line3D", 
         "curve": "KGdB", 
         "end_point": {
          "y": 0.0363582, 
          "x": 0.12031074, 
          "z": 0.0
         }
        }, 
        {
         "start_point": {
          "y": 0.0363582, 
          "x": 0.08981074, 
          "z": 0.0
         }, 
         "type": "Line3D", 
         "curve": "KGZB", 
         "end_point": {
          "y": 0.0363582, 
          "x": 0.12031074, 
          "z": 0.0
         }
        }, 
        {
         "start_point": {
          "y": 0.0363582, 
          "x": 0.08981074, 
          "z": 0.0
         }, 
         "type": "Line3D", 
         "curve": "JGZ", 
         "end_point": {
          "y": 0.0233582, 
          "x": 0.08981074, 
          "z": 0.0
         }
        }, 
        {
         "start_point": {
          "y": 0.0233582, 
          "x": 0.08981074, 
          "z": 0.0
         }, 
         "type": "Line3D", 
         "curve": "JGd", 
         "end_point": {
          "y": 0.0233582, 
          "x": 0.07581074, 
          "z": 0.0
         }
        }, 
        {
         "start_point": {
          "y": 0.0138582, 
          "x": 0.07581074, 
          "z": 0.0
         }, 
         "type": "Line3D", 
         "curve": "JGx", 
         "end_point": {
          "y": 0.0233582, 
          "x": 0.07581074, 
          "z": 0.0
         }
        }, 
        {
         "start_point": {
          "y": 0.0138582, 
          "x": 0.07206074, 
          "z": 0.0
         }, 
         "type": "Line3D", 
         "curve": "JGJ", 
         "end_point": {
          "y": 0.0138582, 
          "x": 0.07581074, 
          "z": 0.0
         }
        }, 
        {
         "start_point": {
          "y": -0.0251418, 
          "x": 0.07206074, 
          "z": 0.0
         }, 
         "type": "Line3D", 
         "curve": "JGF", 
         "end_point": {
          "y": 0.0138582, 
          "x": 0.07206074, 
          "z": 0.0
         }
        }, 
        {
         "start_point": {
          "y": -0.0251418, 
          "x": 0.07206074, 
          "z": 0.0
         }, 
         "type": "Line3D", 
         "curve": "JGR", 
         "end_point": {
          "y": -0.0251418, 
          "x": 0.07581074, 
          "z": 0.0
         }
        }, 
        {
         "start_point": {
          "y": -0.0251418, 
          "x": 0.07581074, 
          "z": 0.0
         }, 
         "type": "Line3D", 
         "curve": "KGpB", 
         "end_point": {
          "y": -0.0521418, 
          "x": 0.07581074, 
          "z": 0.0
         }
        }, 
        {
         "start_point": {
          "y": -0.0521418, 
          "x": 0.08281074, 
          "z": 0.0
         }, 
         "type": "Line3D", 
         "curve": "KGhB", 
         "end_point": {
          "y": -0.0521418, 
          "x": 0.07581074, 
          "z": 0.0
         }
        }, 
        {
         "start_point": {
          "y": -0.0563918, 
          "x": 0.08281074, 
          "z": 0.0
         }, 
         "type": "Line3D", 
         "curve": "KGNB", 
         "end_point": {
          "y": -0.0521418, 
          "x": 0.08281074, 
          "z": 0.0
         }
        }, 
        {
         "start_point": {
          "y": -0.0563918, 
          "x": 0.08281074, 
          "z": 0.0
         }, 
         "type": "Line3D", 
         "curve": "KGJB", 
         "end_point": {
          "y": -0.0563918, 
          "x": 0.11331074, 
          "z": 0.0
         }
        }, 
        {
         "start_point": {
          "y": -0.0563918, 
          "x": 0.11331074, 
          "z": 0.0
         }, 
         "type": "Line3D", 
         "curve": "KGRB", 
         "end_point": {
          "y": -0.0521418, 
          "x": 0.11331074, 
          "z": 0.0
         }
        }, 
        {
         "start_point": {
          "y": -0.0521418, 
          "x": 0.11331074, 
          "z": 0.0
         }, 
         "type": "Line3D", 
         "curve": "KGlB", 
         "end_point": {
          "y": -0.0521418, 
          "x": 0.12031074, 
          "z": 0.0
         }
        }, 
        {
         "start_point": {
          "y": -0.0251418, 
          "x": 0.12031074, 
          "z": 0.0
         }, 
         "type": "Line3D", 
         "curve": "KGtB", 
         "end_point": {
          "y": -0.0521418, 
          "x": 0.12031074, 
          "z": 0.0
         }
        }, 
        {
         "start_point": {
          "y": -0.0251418, 
          "x": 0.12406074, 
          "z": 0.0
         }, 
         "type": "Line3D", 
         "curve": "JGV", 
         "end_point": {
          "y": -0.0251418, 
          "x": 0.12031074, 
          "z": 0.0
         }
        }
       ], 
       "is_outer": true
      }
     ], 
     "properties": {}
    }, 
    "JGe": {
     "loops": [
      {
       "profile_curves": [
        {
         "start_point": {
          "y": 0.0363582, 
          "x": 0.02636154, 
          "z": 0.0
         }, 
         "type": "Line3D", 
         "curve": "KGxB", 
         "end_point": {
          "y": 0.0363582, 
          "x": 0.05686154, 
          "z": 0.0
         }
        }, 
        {
         "start_point": {
          "y": 0.0363582, 
          "x": 0.05686154, 
          "z": 0.0
         }, 
         "type": "Line3D", 
         "curve": "KG5B", 
         "end_point": {
          "y": 0.0138582, 
          "x": 0.05686154, 
          "z": 0.0
         }
        }, 
        {
         "start_point": {
          "y": 0.0138582, 
          "x": 0.05686154, 
          "z": 0.0
         }, 
         "type": "Line3D", 
         "curve": "KGxC", 
         "end_point": {
          "y": 0.0138582, 
          "x": 0.06061154, 
          "z": 0.0
         }
        }, 
        {
         "start_point": {
          "y": -0.0251418, 
          "x": 0.06061154, 
          "z": 0.0
         }, 
         "type": "Line3D", 
         "curve": "KGBC", 
         "end_point": {
          "y": 0.0138582, 
          "x": 0.06061154, 
          "z": 0.0
         }
        }, 
        {
         "start_point": {
          "y": -0.0251418, 
          "x": 0.05686154, 
          "z": 0.0
         }, 
         "type": "Line3D", 
         "curve": "KG5C", 
         "end_point": {
          "y": -0.0251418, 
          "x": 0.06061154, 
          "z": 0.0
         }
        }, 
        {
         "start_point": {
          "y": -0.0251418, 
          "x": 0.05686154, 
          "z": 0.0
         }, 
         "type": "Line3D", 
         "curve": "KG1B", 
         "end_point": {
          "y": -0.0521418, 
          "x": 0.05686154, 
          "z": 0.0
         }
        }, 
        {
         "start_point": {
          "y": -0.0521418, 
          "x": 0.05686154, 
          "z": 0.0
         }, 
         "type": "Line3D", 
         "curve": "KGBD", 
         "end_point": {
          "y": -0.0521418, 
          "x": 0.04986154, 
          "z": 0.0
         }
        }, 
        {
         "start_point": {
          "y": -0.0563918, 
          "x": 0.04986154, 
          "z": 0.0
         }, 
         "type": "Line3D", 
         "curve": "KG1C", 
         "end_point": {
          "y": -0.0521418, 
          "x": 0.04986154, 
          "z": 0.0
         }
        }, 
        {
         "start_point": {
          "y": -0.0563918, 
          "x": 0.01936154, 
          "z": 0.0
         }, 
         "type": "Line3D", 
         "curve": "KGJC", 
         "end_point": {
          "y": -0.0563918, 
          "x": 0.04986154, 
          "z": 0.0
         }
        }, 
        {
         "start_point": {
          "y": -0.0563918, 
          "x": 0.01936154, 
          "z": 0.0
         }, 
         "type": "Line3D", 
         "curve": "KGlC", 
         "end_point": {
          "y": -0.0521418, 
          "x": 0.01936154, 
          "z": 0.0
         }
        }, 
        {
         "start_point": {
          "y": -0.0521418, 
          "x": 0.01236154, 
          "z": 0.0
         }, 
         "type": "Line3D", 
         "curve": "KGdC", 
         "end_point": {
          "y": -0.0521418, 
          "x": 0.01936154, 
          "z": 0.0
         }
        }, 
        {
         "start_point": {
          "y": -0.0251418, 
          "x": 0.01236154, 
          "z": 0.0
         }, 
         "type": "Line3D", 
         "curve": "KGFC", 
         "end_point": {
          "y": -0.0521418, 
          "x": 0.01236154, 
          "z": 0.0
         }
        }, 
        {
         "start_point": {
          "y": -0.0251418, 
          "x": 0.00861154, 
          "z": 0.0
         }, 
         "type": "Line3D", 
         "curve": "KGpC", 
         "end_point": {
          "y": -0.0251418, 
          "x": 0.01236154, 
          "z": 0.0
         }
        }, 
        {
         "start_point": {
          "y": -0.0251418, 
          "x": 0.00861154, 
          "z": 0.0
         }, 
         "type": "Line3D", 
         "curve": "KG9B", 
         "end_point": {
          "y": 0.0138582, 
          "x": 0.00861154, 
          "z": 0.0
         }
        }, 
        {
         "start_point": {
          "y": 0.0138582, 
          "x": 0.00861154, 
          "z": 0.0
         }, 
         "type": "Line3D", 
         "curve": "KG9C", 
         "end_point": {
          "y": 0.0138582, 
          "x": 0.01236154, 
          "z": 0.0
         }
        }, 
        {
         "start_point": {
          "y": 0.0233582, 
          "x": 0.01236154, 
          "z": 0.0
         }, 
         "type": "Line3D", 
         "curve": "KGZC", 
         "end_point": {
          "y": 0.0138582, 
          "x": 0.01236154, 
          "z": 0.0
         }
        }, 
        {
         "start_point": {
          "y": 0.0233582, 
          "x": 0.02636154, 
          "z": 0.0
         }, 
         "type": "Line3D", 
         "curve": "KGNC", 
         "end_point": {
          "y": 0.0233582, 
          "x": 0.01236154, 
          "z": 0.0
         }
        }, 
        {
         "start_point": {
          "y": 0.0363582, 
          "x": 0.02636154, 
          "z": 0.0
         }, 
         "type": "Line3D", 
         "curve": "KGtC", 
         "end_point": {
          "y": 0.0233582, 
          "x": 0.02636154, 
          "z": 0.0
         }
        }
       ], 
       "is_outer": true
      }
     ], 
     "properties": {}
    }, 
    "KGeB": {
     "loops": [
      {
       "profile_curves": [
        {
         "center_point": {
          "y": 0.06573337, 
          "x": -0.09229132, 
          "z": 0.0
         }, 
         "radius": 0.0025, 
         "type": "Circle3D", 
         "curve": "KGVF", 
         "normal": {
          "y": 0.0, 
          "x": 0.0, 
          "z": 1.0
         }
        }
       ], 
       "is_outer": true
      }
     ], 
     "properties": {}
    }, 
    "KGCB": {
     "loops": [
      {
       "profile_curves": [
        {
         "center_point": {
          "y": 0.06573337, 
          "x": -0.02884212, 
          "z": 0.0
         }, 
         "radius": 0.0025, 
         "type": "Circle3D", 
         "curve": "KG1D", 
         "normal": {
          "y": 0.0, 
          "x": 0.0, 
          "z": 1.0
         }
        }
       ], 
       "is_outer": true
      }
     ], 
     "properties": {}
    }, 
    "JGS": {
     "loops": [
      {
       "profile_curves": [
        {
         "center_point": {
          "y": 0.0283582, 
          "x": 0.08054928, 
          "z": 0.0
         }, 
         "radius": 0.00065, 
         "type": "Circle3D", 
         "curve": "JGt", 
         "normal": {
          "y": 0.0, 
          "x": 0.0, 
          "z": 1.0
         }
        }
       ], 
       "is_outer": true
      }
     ], 
     "properties": {}
    }, 
    "KGiB": {
     "loops": [
      {
       "profile_curves": [
        {
         "center_point": {
          "y": 0.0283582, 
          "x": -0.10979832, 
          "z": 0.0
         }, 
         "radius": 0.00065, 
         "type": "Circle3D", 
         "curve": "KGhF", 
         "normal": {
          "y": 0.0, 
          "x": 0.0, 
          "z": 1.0
         }
        }
       ], 
       "is_outer": true
      }
     ], 
     "properties": {}
    }, 
    "KGmB": {
     "loops": [
      {
       "profile_curves": [
        {
         "center_point": {
          "y": 0.0283582, 
          "x": -0.10733832, 
          "z": 0.0
         }, 
         "radius": 0.00065, 
         "type": "Circle3D", 
         "curve": "KGFG", 
         "normal": {
          "y": 0.0, 
          "x": 0.0, 
          "z": 1.0
         }
        }
       ], 
       "is_outer": true
      }
     ], 
     "properties": {}
    }, 
    "KGGB": {
     "loops": [
      {
       "profile_curves": [
        {
         "center_point": {
          "y": 0.0283582, 
          "x": -0.04634912, 
          "z": 0.0
         }, 
         "radius": 0.00065, 
         "type": "Circle3D", 
         "curve": "KGBE", 
         "normal": {
          "y": 0.0, 
          "x": 0.0, 
          "z": 1.0
         }
        }
       ], 
       "is_outer": true
      }
     ], 
     "properties": {}
    }, 
    "JGG": {
     "loops": [
      {
       "profile_curves": [
        {
         "center_point": {
          "y": 0.0283582, 
          "x": 0.08792928, 
          "z": 0.0
         }, 
         "radius": 0.00065, 
         "type": "Circle3D", 
         "curve": "JGh", 
         "normal": {
          "y": 0.0, 
          "x": 0.0, 
          "z": 1.0
         }
        }
       ], 
       "is_outer": true
      }
     ], 
     "properties": {}
    }, 
    "KGSB": {
     "loops": [
      {
       "profile_curves": [
        {
         "center_point": {
          "y": 0.0283582, 
          "x": -0.03896912, 
          "z": 0.0
         }, 
         "radius": 0.00065, 
         "type": "Circle3D", 
         "curve": "KGtE", 
         "normal": {
          "y": 0.0, 
          "x": 0.0, 
          "z": 1.0
         }
        }
       ], 
       "is_outer": true
      }
     ], 
     "properties": {}
    }, 
    "JGi": {
     "loops": [
      {
       "profile_curves": [
        {
         "center_point": {
          "y": 0.0482582, 
          "x": 0.03290408, 
          "z": 0.0
         }, 
         "radius": 0.001905, 
         "type": "Circle3D", 
         "curve": "KGRC", 
         "normal": {
          "y": 0.0, 
          "x": 0.0, 
          "z": 1.0
         }
        }
       ], 
       "is_outer": true
      }
     ], 
     "properties": {}
    }, 
    "JG+": {
     "loops": [
      {
       "profile_curves": [
        {
         "center_point": {
          "y": 0.0482582, 
          "x": -0.03054512, 
          "z": 0.0
         }, 
         "radius": 0.001905, 
         "type": "Circle3D", 
         "curve": "KGxD", 
         "normal": {
          "y": 0.0, 
          "x": 0.0, 
          "z": 1.0
         }
        }
       ], 
       "is_outer": true
      }
     ], 
     "properties": {}
    }, 
    "JGm": {
     "loops": [
      {
       "profile_curves": [
        {
         "center_point": {
          "y": 0.06573337, 
          "x": 0.03460708, 
          "z": 0.0
         }, 
         "radius": 0.0025, 
         "type": "Circle3D", 
         "curve": "KGVC", 
         "normal": {
          "y": 0.0, 
          "x": 0.0, 
          "z": 1.0
         }
        }
       ], 
       "is_outer": true
      }
     ], 
     "properties": {}
    }, 
    "JGy": {
     "loops": [
      {
       "profile_curves": [
        {
         "center_point": {
          "y": 0.0283582, 
          "x": 0.02202008, 
          "z": 0.0
         }, 
         "radius": 0.00065, 
         "type": "Circle3D", 
         "curve": "KGJD", 
         "normal": {
          "y": 0.0, 
          "x": 0.0, 
          "z": 1.0
         }
        }
       ], 
       "is_outer": true
      }
     ], 
     "properties": {}
    }, 
    "JGa": {
     "loops": [
      {
       "profile_curves": [
        {
         "center_point": {
          "y": 0.06573337, 
          "x": 0.09805628, 
          "z": 0.0
         }, 
         "radius": 0.0025, 
         "type": "Circle3D", 
         "curve": "KGVB", 
         "normal": {
          "y": 0.0, 
          "x": 0.0, 
          "z": 1.0
         }
        }
       ], 
       "is_outer": true
      }
     ], 
     "properties": {}
    }, 
    "KGyB": {
     "loops": [
      {
       "profile_curves": [
        {
         "start_point": {
          "y": -0.0251418, 
          "x": 0.12406074, 
          "z": 0.0
         }, 
         "type": "Line3D", 
         "curve": "JGB", 
         "end_point": {
          "y": 0.0138582, 
          "x": 0.12406074, 
          "z": 0.0
         }
        }, 
        {
         "start_point": {
          "y": 0.0138582, 
          "x": 0.12406074, 
          "z": 0.0
         }, 
         "type": "Line3D", 
         "curve": "JGN", 
         "end_point": {
          "y": 0.0138582, 
          "x": 0.12031074, 
          "z": 0.0
         }
        }, 
        {
         "start_point": {
          "y": 0.0138582, 
          "x": 0.12031074, 
          "z": 0.0
         }, 
         "type": "Line3D", 
         "curve": "KGdB", 
         "end_point": {
          "y": 0.0363582, 
          "x": 0.12031074, 
          "z": 0.0
         }
        }, 
        {
         "start_point": {
          "y": 0.0363582, 
          "x": 0.08981074, 
          "z": 0.0
         }, 
         "type": "Line3D", 
         "curve": "KGZB", 
         "end_point": {
          "y": 0.0363582, 
          "x": 0.12031074, 
          "z": 0.0
         }
        }, 
        {
         "start_point": {
          "y": 0.0363582, 
          "x": 0.08981074, 
          "z": 0.0
         }, 
         "type": "Line3D", 
         "curve": "JGZ", 
         "end_point": {
          "y": 0.0233582, 
          "x": 0.08981074, 
          "z": 0.0
         }
        }, 
        {
         "start_point": {
          "y": 0.0233582, 
          "x": 0.08981074, 
          "z": 0.0
         }, 
         "type": "Line3D", 
         "curve": "JGd", 
         "end_point": {
          "y": 0.0233582, 
          "x": 0.07581074, 
          "z": 0.0
         }
        }, 
        {
         "start_point": {
          "y": 0.0138582, 
          "x": 0.07581074, 
          "z": 0.0
         }, 
         "type": "Line3D", 
         "curve": "JGx", 
         "end_point": {
          "y": 0.0233582, 
          "x": 0.07581074, 
          "z": 0.0
         }
        }, 
        {
         "start_point": {
          "y": 0.0138582, 
          "x": 0.07206074, 
          "z": 0.0
         }, 
         "type": "Line3D", 
         "curve": "JGJ", 
         "end_point": {
          "y": 0.0138582, 
          "x": 0.07581074, 
          "z": 0.0
         }
        }, 
        {
         "start_point": {
          "y": -0.0251418, 
          "x": 0.07206074, 
          "z": 0.0
         }, 
         "type": "Line3D", 
         "curve": "JGF", 
         "end_point": {
          "y": 0.0138582, 
          "x": 0.07206074, 
          "z": 0.0
         }
        }, 
        {
         "start_point": {
          "y": -0.0251418, 
          "x": 0.07206074, 
          "z": 0.0
         }, 
         "type": "Line3D", 
         "curve": "JGR", 
         "end_point": {
          "y": -0.0251418, 
          "x": 0.07581074, 
          "z": 0.0
         }
        }, 
        {
         "start_point": {
          "y": -0.0251418, 
          "x": 0.07581074, 
          "z": 0.0
         }, 
         "type": "Line3D", 
         "curve": "KGpB", 
         "end_point": {
          "y": -0.0521418, 
          "x": 0.07581074, 
          "z": 0.0
         }
        }, 
        {
         "start_point": {
          "y": -0.0521418, 
          "x": 0.08281074, 
          "z": 0.0
         }, 
         "type": "Line3D", 
         "curve": "KGhB", 
         "end_point": {
          "y": -0.0521418, 
          "x": 0.07581074, 
          "z": 0.0
         }
        }, 
        {
         "start_point": {
          "y": -0.0563918, 
          "x": 0.08281074, 
          "z": 0.0
         }, 
         "type": "Line3D", 
         "curve": "KGNB", 
         "end_point": {
          "y": -0.0521418, 
          "x": 0.08281074, 
          "z": 0.0
         }
        }, 
        {
         "start_point": {
          "y": -0.0563918, 
          "x": 0.08281074, 
          "z": 0.0
         }, 
         "type": "Line3D", 
         "curve": "KGJB", 
         "end_point": {
          "y": -0.0563918, 
          "x": 0.11331074, 
          "z": 0.0
         }
        }, 
        {
         "start_point": {
          "y": -0.0563918, 
          "x": 0.11331074, 
          "z": 0.0
         }, 
         "type": "Line3D", 
         "curve": "KGRB", 
         "end_point": {
          "y": -0.0521418, 
          "x": 0.11331074, 
          "z": 0.0
         }
        }, 
        {
         "start_point": {
          "y": -0.0521418, 
          "x": 0.11331074, 
          "z": 0.0
         }, 
         "type": "Line3D", 
         "curve": "KGlB", 
         "end_point": {
          "y": -0.0521418, 
          "x": 0.12031074, 
          "z": 0.0
         }
        }, 
        {
         "start_point": {
          "y": -0.0251418, 
          "x": 0.12031074, 
          "z": 0.0
         }, 
         "type": "Line3D", 
         "curve": "KGtB", 
         "end_point": {
          "y": -0.0521418, 
          "x": 0.12031074, 
          "z": 0.0
         }
        }, 
        {
         "start_point": {
          "y": -0.0251418, 
          "x": 0.12406074, 
          "z": 0.0
         }, 
         "type": "Line3D", 
         "curve": "JGV", 
         "end_point": {
          "y": -0.0251418, 
          "x": 0.12031074, 
          "z": 0.0
         }
        }
       ], 
       "is_outer": true
      }, 
      {
       "profile_curves": [
        {
         "center_point": {
          "y": 0.0283582, 
          "x": 0.08792928, 
          "z": 0.0
         }, 
         "radius": 0.00065, 
         "type": "Circle3D", 
         "curve": "JGh", 
         "normal": {
          "y": 0.0, 
          "x": 0.0, 
          "z": 1.0
         }
        }
       ], 
       "is_outer": true
      }, 
      {
       "profile_curves": [
        {
         "center_point": {
          "y": 0.0283582, 
          "x": 0.08546928, 
          "z": 0.0
         }, 
         "radius": 0.00065, 
         "type": "Circle3D", 
         "curve": "JGl", 
         "normal": {
          "y": 0.0, 
          "x": 0.0, 
          "z": 1.0
         }
        }
       ], 
       "is_outer": true
      }, 
      {
       "profile_curves": [
        {
         "center_point": {
          "y": 0.0283582, 
          "x": 0.08300928, 
          "z": 0.0
         }, 
         "radius": 0.00065, 
         "type": "Circle3D", 
         "curve": "JGp", 
         "normal": {
          "y": 0.0, 
          "x": 0.0, 
          "z": 1.0
         }
        }
       ], 
       "is_outer": true
      }, 
      {
       "profile_curves": [
        {
         "center_point": {
          "y": 0.0283582, 
          "x": 0.08054928, 
          "z": 0.0
         }, 
         "radius": 0.00065, 
         "type": "Circle3D", 
         "curve": "JGt", 
         "normal": {
          "y": 0.0, 
          "x": 0.0, 
          "z": 1.0
         }
        }
       ], 
       "is_outer": true
      }, 
      {
       "profile_curves": [
        {
         "start_point": {
          "y": 0.0869702, 
          "x": -0.1265242, 
          "z": 0.0
         }, 
         "type": "Line3D", 
         "curve": "JG1", 
         "end_point": {
          "y": 0.0869702, 
          "x": 0.1314758, 
          "z": 0.0
         }
        }, 
        {
         "start_point": {
          "y": 0.0869702, 
          "x": 0.1314758, 
          "z": 0.0
         }, 
         "type": "Line3D", 
         "curve": "KGBB", 
         "end_point": {
          "y": -0.1370298, 
          "x": 0.1314758, 
          "z": 0.0
         }
        }, 
        {
         "start_point": {
          "y": -0.1370298, 
          "x": -0.1265242, 
          "z": 0.0
         }, 
         "type": "Line3D", 
         "curve": "JG5", 
         "end_point": {
          "y": -0.1370298, 
          "x": 0.1314758, 
          "z": 0.0
         }
        }, 
        {
         "start_point": {
          "y": 0.0869702, 
          "x": -0.1265242, 
          "z": 0.0
         }, 
         "type": "Line3D", 
         "curve": "JG9", 
         "end_point": {
          "y": -0.1370298, 
          "x": -0.1265242, 
          "z": 0.0
         }
        }
       ], 
       "is_outer": true
      }, 
      {
       "profile_curves": [
        {
         "center_point": {
          "y": 0.0482582, 
          "x": 0.09635328, 
          "z": 0.0
         }, 
         "radius": 0.001905, 
         "type": "Circle3D", 
         "curve": "KGFB", 
         "normal": {
          "y": 0.0, 
          "x": 0.0, 
          "z": 1.0
         }
        }
       ], 
       "is_outer": true
      }, 
      {
       "profile_curves": [
        {
         "center_point": {
          "y": 0.06573337, 
          "x": 0.09805628, 
          "z": 0.0
         }, 
         "radius": 0.0025, 
         "type": "Circle3D", 
         "curve": "KGVB", 
         "normal": {
          "y": 0.0, 
          "x": 0.0, 
          "z": 1.0
         }
        }
       ], 
       "is_outer": true
      }, 
      {
       "profile_curves": [
        {
         "start_point": {
          "y": 0.0363582, 
          "x": 0.02636154, 
          "z": 0.0
         }, 
         "type": "Line3D", 
         "curve": "KGxB", 
         "end_point": {
          "y": 0.0363582, 
          "x": 0.05686154, 
          "z": 0.0
         }
        }, 
        {
         "start_point": {
          "y": 0.0363582, 
          "x": 0.05686154, 
          "z": 0.0
         }, 
         "type": "Line3D", 
         "curve": "KG5B", 
         "end_point": {
          "y": 0.0138582, 
          "x": 0.05686154, 
          "z": 0.0
         }
        }, 
        {
         "start_point": {
          "y": 0.0138582, 
          "x": 0.05686154, 
          "z": 0.0
         }, 
         "type": "Line3D", 
         "curve": "KGxC", 
         "end_point": {
          "y": 0.0138582, 
          "x": 0.06061154, 
          "z": 0.0
         }
        }, 
        {
         "start_point": {
          "y": -0.0251418, 
          "x": 0.06061154, 
          "z": 0.0
         }, 
         "type": "Line3D", 
         "curve": "KGBC", 
         "end_point": {
          "y": 0.0138582, 
          "x": 0.06061154, 
          "z": 0.0
         }
        }, 
        {
         "start_point": {
          "y": -0.0251418, 
          "x": 0.05686154, 
          "z": 0.0
         }, 
         "type": "Line3D", 
         "curve": "KG5C", 
         "end_point": {
          "y": -0.0251418, 
          "x": 0.06061154, 
          "z": 0.0
         }
        }, 
        {
         "start_point": {
          "y": -0.0251418, 
          "x": 0.05686154, 
          "z": 0.0
         }, 
         "type": "Line3D", 
         "curve": "KG1B", 
         "end_point": {
          "y": -0.0521418, 
          "x": 0.05686154, 
          "z": 0.0
         }
        }, 
        {
         "start_point": {
          "y": -0.0521418, 
          "x": 0.05686154, 
          "z": 0.0
         }, 
         "type": "Line3D", 
         "curve": "KGBD", 
         "end_point": {
          "y": -0.0521418, 
          "x": 0.04986154, 
          "z": 0.0
         }
        }, 
        {
         "start_point": {
          "y": -0.0563918, 
          "x": 0.04986154, 
          "z": 0.0
         }, 
         "type": "Line3D", 
         "curve": "KG1C", 
         "end_point": {
          "y": -0.0521418, 
          "x": 0.04986154, 
          "z": 0.0
         }
        }, 
        {
         "start_point": {
          "y": -0.0563918, 
          "x": 0.01936154, 
          "z": 0.0
         }, 
         "type": "Line3D", 
         "curve": "KGJC", 
         "end_point": {
          "y": -0.0563918, 
          "x": 0.04986154, 
          "z": 0.0
         }
        }, 
        {
         "start_point": {
          "y": -0.0563918, 
          "x": 0.01936154, 
          "z": 0.0
         }, 
         "type": "Line3D", 
         "curve": "KGlC", 
         "end_point": {
          "y": -0.0521418, 
          "x": 0.01936154, 
          "z": 0.0
         }
        }, 
        {
         "start_point": {
          "y": -0.0521418, 
          "x": 0.01236154, 
          "z": 0.0
         }, 
         "type": "Line3D", 
         "curve": "KGdC", 
         "end_point": {
          "y": -0.0521418, 
          "x": 0.01936154, 
          "z": 0.0
         }
        }, 
        {
         "start_point": {
          "y": -0.0251418, 
          "x": 0.01236154, 
          "z": 0.0
         }, 
         "type": "Line3D", 
         "curve": "KGFC", 
         "end_point": {
          "y": -0.0521418, 
          "x": 0.01236154, 
          "z": 0.0
         }
        }, 
        {
         "start_point": {
          "y": -0.0251418, 
          "x": 0.00861154, 
          "z": 0.0
         }, 
         "type": "Line3D", 
         "curve": "KGpC", 
         "end_point": {
          "y": -0.0251418, 
          "x": 0.01236154, 
          "z": 0.0
         }
        }, 
        {
         "start_point": {
          "y": -0.0251418, 
          "x": 0.00861154, 
          "z": 0.0
         }, 
         "type": "Line3D", 
         "curve": "KG9B", 
         "end_point": {
          "y": 0.0138582, 
          "x": 0.00861154, 
          "z": 0.0
         }
        }, 
        {
         "start_point": {
          "y": 0.0138582, 
          "x": 0.00861154, 
          "z": 0.0
         }, 
         "type": "Line3D", 
         "curve": "KG9C", 
         "end_point": {
          "y": 0.0138582, 
          "x": 0.01236154, 
          "z": 0.0
         }
        }, 
        {
         "start_point": {
          "y": 0.0233582, 
          "x": 0.01236154, 
          "z": 0.0
         }, 
         "type": "Line3D", 
         "curve": "KGZC", 
         "end_point": {
          "y": 0.0138582, 
          "x": 0.01236154, 
          "z": 0.0
         }
        }, 
        {
         "start_point": {
          "y": 0.0233582, 
          "x": 0.02636154, 
          "z": 0.0
         }, 
         "type": "Line3D", 
         "curve": "KGNC", 
         "end_point": {
          "y": 0.0233582, 
          "x": 0.01236154, 
          "z": 0.0
         }
        }, 
        {
         "start_point": {
          "y": 0.0363582, 
          "x": 0.02636154, 
          "z": 0.0
         }, 
         "type": "Line3D", 
         "curve": "KGtC", 
         "end_point": {
          "y": 0.0233582, 
          "x": 0.02636154, 
          "z": 0.0
         }
        }
       ], 
       "is_outer": true
      }, 
      {
       "profile_curves": [
        {
         "center_point": {
          "y": 0.0482582, 
          "x": 0.03290408, 
          "z": 0.0
         }, 
         "radius": 0.001905, 
         "type": "Circle3D", 
         "curve": "KGRC", 
         "normal": {
          "y": 0.0, 
          "x": 0.0, 
          "z": 1.0
         }
        }
       ], 
       "is_outer": true
      }, 
      {
       "profile_curves": [
        {
         "center_point": {
          "y": 0.06573337, 
          "x": 0.03460708, 
          "z": 0.0
         }, 
         "radius": 0.0025, 
         "type": "Circle3D", 
         "curve": "KGVC", 
         "normal": {
          "y": 0.0, 
          "x": 0.0, 
          "z": 1.0
         }
        }
       ], 
       "is_outer": true
      }, 
      {
       "profile_curves": [
        {
         "center_point": {
          "y": 0.0283582, 
          "x": 0.01710008, 
          "z": 0.0
         }, 
         "radius": 0.00065, 
         "type": "Circle3D", 
         "curve": "KGhC", 
         "normal": {
          "y": 0.0, 
          "x": 0.0, 
          "z": 1.0
         }
        }
       ], 
       "is_outer": true
      }, 
      {
       "profile_curves": [
        {
         "center_point": {
          "y": 0.0283582, 
          "x": 0.01956008, 
          "z": 0.0
         }, 
         "radius": 0.00065, 
         "type": "Circle3D", 
         "curve": "KGFD", 
         "normal": {
          "y": 0.0, 
          "x": 0.0, 
          "z": 1.0
         }
        }
       ], 
       "is_outer": true
      }, 
      {
       "profile_curves": [
        {
         "center_point": {
          "y": 0.0283582, 
          "x": 0.02202008, 
          "z": 0.0
         }, 
         "radius": 0.00065, 
         "type": "Circle3D", 
         "curve": "KGJD", 
         "normal": {
          "y": 0.0, 
          "x": 0.0, 
          "z": 1.0
         }
        }
       ], 
       "is_outer": true
      }, 
      {
       "profile_curves": [
        {
         "center_point": {
          "y": 0.0283582, 
          "x": 0.02448008, 
          "z": 0.0
         }, 
         "radius": 0.00065, 
         "type": "Circle3D", 
         "curve": "KGND", 
         "normal": {
          "y": 0.0, 
          "x": 0.0, 
          "z": 1.0
         }
        }
       ], 
       "is_outer": true
      }, 
      {
       "profile_curves": [
        {
         "start_point": {
          "y": 0.0363582, 
          "x": -0.03708766, 
          "z": 0.0
         }, 
         "type": "Line3D", 
         "curve": "KGRD", 
         "end_point": {
          "y": 0.0363582, 
          "x": -0.00658766, 
          "z": 0.0
         }
        }, 
        {
         "start_point": {
          "y": 0.0363582, 
          "x": -0.00658766, 
          "z": 0.0
         }, 
         "type": "Line3D", 
         "curve": "KGZD", 
         "end_point": {
          "y": 0.0138582, 
          "x": -0.00658766, 
          "z": 0.0
         }
        }, 
        {
         "start_point": {
          "y": 0.0138582, 
          "x": -0.00658766, 
          "z": 0.0
         }, 
         "type": "Line3D", 
         "curve": "KGRE", 
         "end_point": {
          "y": 0.0138582, 
          "x": -0.00283766, 
          "z": 0.0
         }
        }, 
        {
         "start_point": {
          "y": -0.0251418, 
          "x": -0.00283766, 
          "z": 0.0
         }, 
         "type": "Line3D", 
         "curve": "KGhD", 
         "end_point": {
          "y": 0.0138582, 
          "x": -0.00283766, 
          "z": 0.0
         }
        }, 
        {
         "start_point": {
          "y": -0.0251418, 
          "x": -0.00658766, 
          "z": 0.0
         }, 
         "type": "Line3D", 
         "curve": "KGZE", 
         "end_point": {
          "y": -0.0251418, 
          "x": -0.00283766, 
          "z": 0.0
         }
        }, 
        {
         "start_point": {
          "y": -0.0251418, 
          "x": -0.00658766, 
          "z": 0.0
         }, 
         "type": "Line3D", 
         "curve": "KGVD", 
         "end_point": {
          "y": -0.0521418, 
          "x": -0.00658766, 
          "z": 0.0
         }
        }, 
        {
         "start_point": {
          "y": -0.0521418, 
          "x": -0.00658766, 
          "z": 0.0
         }, 
         "type": "Line3D", 
         "curve": "KGhE", 
         "end_point": {
          "y": -0.0521418, 
          "x": -0.01358766, 
          "z": 0.0
         }
        }, 
        {
         "start_point": {
          "y": -0.0563918, 
          "x": -0.01358766, 
          "z": 0.0
         }, 
         "type": "Line3D", 
         "curve": "KGVE", 
         "end_point": {
          "y": -0.0521418, 
          "x": -0.01358766, 
          "z": 0.0
         }
        }, 
        {
         "start_point": {
          "y": -0.0563918, 
          "x": -0.04408766, 
          "z": 0.0
         }, 
         "type": "Line3D", 
         "curve": "KGpD", 
         "end_point": {
          "y": -0.0563918, 
          "x": -0.01358766, 
          "z": 0.0
         }
        }, 
        {
         "start_point": {
          "y": -0.0563918, 
          "x": -0.04408766, 
          "z": 0.0
         }, 
         "type": "Line3D", 
         "curve": "KGFE", 
         "end_point": {
          "y": -0.0521418, 
          "x": -0.04408766, 
          "z": 0.0
         }
        }, 
        {
         "start_point": {
          "y": -0.0521418, 
          "x": -0.05108766, 
          "z": 0.0
         }, 
         "type": "Line3D", 
         "curve": "KG9D", 
         "end_point": {
          "y": -0.0521418, 
          "x": -0.04408766, 
          "z": 0.0
         }
        }, 
        {
         "start_point": {
          "y": -0.0251418, 
          "x": -0.05108766, 
          "z": 0.0
         }, 
         "type": "Line3D", 
         "curve": "KGlD", 
         "end_point": {
          "y": -0.0521418, 
          "x": -0.05108766, 
          "z": 0.0
         }
        }, 
        {
         "start_point": {
          "y": -0.0251418, 
          "x": -0.05483766, 
          "z": 0.0
         }, 
         "type": "Line3D", 
         "curve": "KGJE", 
         "end_point": {
          "y": -0.0251418, 
          "x": -0.05108766, 
          "z": 0.0
         }
        }, 
        {
         "start_point": {
          "y": -0.0251418, 
          "x": -0.05483766, 
          "z": 0.0
         }, 
         "type": "Line3D", 
         "curve": "KGdD", 
         "end_point": {
          "y": 0.0138582, 
          "x": -0.05483766, 
          "z": 0.0
         }
        }, 
        {
         "start_point": {
          "y": 0.0138582, 
          "x": -0.05483766, 
          "z": 0.0
         }, 
         "type": "Line3D", 
         "curve": "KGdE", 
         "end_point": {
          "y": 0.0138582, 
          "x": -0.05108766, 
          "z": 0.0
         }
        }, 
        {
         "start_point": {
          "y": 0.0233582, 
          "x": -0.05108766, 
          "z": 0.0
         }, 
         "type": "Line3D", 
         "curve": "KG5D", 
         "end_point": {
          "y": 0.0138582, 
          "x": -0.05108766, 
          "z": 0.0
         }
        }, 
        {
         "start_point": {
          "y": 0.0233582, 
          "x": -0.03708766, 
          "z": 0.0
         }, 
         "type": "Line3D", 
         "curve": "KGtD", 
         "end_point": {
          "y": 0.0233582, 
          "x": -0.05108766, 
          "z": 0.0
         }
        }, 
        {
         "start_point": {
          "y": 0.0363582, 
          "x": -0.03708766, 
          "z": 0.0
         }, 
         "type": "Line3D", 
         "curve": "KGNE", 
         "end_point": {
          "y": 0.0233582, 
          "x": -0.03708766, 
          "z": 0.0
         }
        }
       ], 
       "is_outer": true
      }, 
      {
       "profile_curves": [
        {
         "center_point": {
          "y": 0.0482582, 
          "x": -0.03054512, 
          "z": 0.0
         }, 
         "radius": 0.001905, 
         "type": "Circle3D", 
         "curve": "KGxD", 
         "normal": {
          "y": 0.0, 
          "x": 0.0, 
          "z": 1.0
         }
        }
       ], 
       "is_outer": true
      }, 
      {
       "profile_curves": [
        {
         "center_point": {
          "y": 0.06573337, 
          "x": -0.02884212, 
          "z": 0.0
         }, 
         "radius": 0.0025, 
         "type": "Circle3D", 
         "curve": "KG1D", 
         "normal": {
          "y": 0.0, 
          "x": 0.0, 
          "z": 1.0
         }
        }
       ], 
       "is_outer": true
      }, 
      {
       "profile_curves": [
        {
         "center_point": {
          "y": 0.0283582, 
          "x": -0.04634912, 
          "z": 0.0
         }, 
         "radius": 0.00065, 
         "type": "Circle3D", 
         "curve": "KGBE", 
         "normal": {
          "y": 0.0, 
          "x": 0.0, 
          "z": 1.0
         }
        }
       ], 
       "is_outer": true
      }, 
      {
       "profile_curves": [
        {
         "center_point": {
          "y": 0.0283582, 
          "x": -0.04388912, 
          "z": 0.0
         }, 
         "radius": 0.00065, 
         "type": "Circle3D", 
         "curve": "KGlE", 
         "normal": {
          "y": 0.0, 
          "x": 0.0, 
          "z": 1.0
         }
        }
       ], 
       "is_outer": true
      }, 
      {
       "profile_curves": [
        {
         "center_point": {
          "y": 0.0283582, 
          "x": -0.04142912, 
          "z": 0.0
         }, 
         "radius": 0.00065, 
         "type": "Circle3D", 
         "curve": "KGpE", 
         "normal": {
          "y": 0.0, 
          "x": 0.0, 
          "z": 1.0
         }
        }
       ], 
       "is_outer": true
      }, 
      {
       "profile_curves": [
        {
         "center_point": {
          "y": 0.0283582, 
          "x": -0.03896912, 
          "z": 0.0
         }, 
         "radius": 0.00065, 
         "type": "Circle3D", 
         "curve": "KGtE", 
         "normal": {
          "y": 0.0, 
          "x": 0.0, 
          "z": 1.0
         }
        }
       ], 
       "is_outer": true
      }, 
      {
       "profile_curves": [
        {
         "start_point": {
          "y": 0.0363582, 
          "x": -0.10053686, 
          "z": 0.0
         }, 
         "type": "Line3D", 
         "curve": "KGxE", 
         "end_point": {
          "y": 0.0363582, 
          "x": -0.07003686, 
          "z": 0.0
         }
        }, 
        {
         "start_point": {
          "y": 0.0363582, 
          "x": -0.07003686, 
          "z": 0.0
         }, 
         "type": "Line3D", 
         "curve": "KG5E", 
         "end_point": {
          "y": 0.0138582, 
          "x": -0.07003686, 
          "z": 0.0
         }
        }, 
        {
         "start_point": {
          "y": 0.0138582, 
          "x": -0.07003686, 
          "z": 0.0
         }, 
         "type": "Line3D", 
         "curve": "KGxF", 
         "end_point": {
          "y": 0.0138582, 
          "x": -0.06628686, 
          "z": 0.0
         }
        }, 
        {
         "start_point": {
          "y": -0.0251418, 
          "x": -0.06628686, 
          "z": 0.0
         }, 
         "type": "Line3D", 
         "curve": "KGBF", 
         "end_point": {
          "y": 0.0138582, 
          "x": -0.06628686, 
          "z": 0.0
         }
        }, 
        {
         "start_point": {
          "y": -0.0251418, 
          "x": -0.07003686, 
          "z": 0.0
         }, 
         "type": "Line3D", 
         "curve": "KG5F", 
         "end_point": {
          "y": -0.0251418, 
          "x": -0.06628686, 
          "z": 0.0
         }
        }, 
        {
         "start_point": {
          "y": -0.0251418, 
          "x": -0.07003686, 
          "z": 0.0
         }, 
         "type": "Line3D", 
         "curve": "KG1E", 
         "end_point": {
          "y": -0.0521418, 
          "x": -0.07003686, 
          "z": 0.0
         }
        }, 
        {
         "start_point": {
          "y": -0.0521418, 
          "x": -0.07003686, 
          "z": 0.0
         }, 
         "type": "Line3D", 
         "curve": "KGBG", 
         "end_point": {
          "y": -0.0521418, 
          "x": -0.07703686, 
          "z": 0.0
         }
        }, 
        {
         "start_point": {
          "y": -0.0563918, 
          "x": -0.07703686, 
          "z": 0.0
         }, 
         "type": "Line3D", 
         "curve": "KG1F", 
         "end_point": {
          "y": -0.0521418, 
          "x": -0.07703686, 
          "z": 0.0
         }
        }, 
        {
         "start_point": {
          "y": -0.0563918, 
          "x": -0.10753686, 
          "z": 0.0
         }, 
         "type": "Line3D", 
         "curve": "KGJF", 
         "end_point": {
          "y": -0.0563918, 
          "x": -0.07703686, 
          "z": 0.0
         }
        }, 
        {
         "start_point": {
          "y": -0.0563918, 
          "x": -0.10753686, 
          "z": 0.0
         }, 
         "type": "Line3D", 
         "curve": "KGlF", 
         "end_point": {
          "y": -0.0521418, 
          "x": -0.10753686, 
          "z": 0.0
         }
        }, 
        {
         "start_point": {
          "y": -0.0521418, 
          "x": -0.11453686, 
          "z": 0.0
         }, 
         "type": "Line3D", 
         "curve": "KGdF", 
         "end_point": {
          "y": -0.0521418, 
          "x": -0.10753686, 
          "z": 0.0
         }
        }, 
        {
         "start_point": {
          "y": -0.0251418, 
          "x": -0.11453686, 
          "z": 0.0
         }, 
         "type": "Line3D", 
         "curve": "KGFF", 
         "end_point": {
          "y": -0.0521418, 
          "x": -0.11453686, 
          "z": 0.0
         }
        }, 
        {
         "start_point": {
          "y": -0.0251418, 
          "x": -0.11828686, 
          "z": 0.0
         }, 
         "type": "Line3D", 
         "curve": "KGpF", 
         "end_point": {
          "y": -0.0251418, 
          "x": -0.11453686, 
          "z": 0.0
         }
        }, 
        {
         "start_point": {
          "y": -0.0251418, 
          "x": -0.11828686, 
          "z": 0.0
         }, 
         "type": "Line3D", 
         "curve": "KG9E", 
         "end_point": {
          "y": 0.0138582, 
          "x": -0.11828686, 
          "z": 0.0
         }
        }, 
        {
         "start_point": {
          "y": 0.0138582, 
          "x": -0.11828686, 
          "z": 0.0
         }, 
         "type": "Line3D", 
         "curve": "KG9F", 
         "end_point": {
          "y": 0.0138582, 
          "x": -0.11453686, 
          "z": 0.0
         }
        }, 
        {
         "start_point": {
          "y": 0.0233582, 
          "x": -0.11453686, 
          "z": 0.0
         }, 
         "type": "Line3D", 
         "curve": "KGZF", 
         "end_point": {
          "y": 0.0138582, 
          "x": -0.11453686, 
          "z": 0.0
         }
        }, 
        {
         "start_point": {
          "y": 0.0233582, 
          "x": -0.10053686, 
          "z": 0.0
         }, 
         "type": "Line3D", 
         "curve": "KGNF", 
         "end_point": {
          "y": 0.0233582, 
          "x": -0.11453686, 
          "z": 0.0
         }
        }, 
        {
         "start_point": {
          "y": 0.0363582, 
          "x": -0.10053686, 
          "z": 0.0
         }, 
         "type": "Line3D", 
         "curve": "KGtF", 
         "end_point": {
          "y": 0.0233582, 
          "x": -0.10053686, 
          "z": 0.0
         }
        }
       ], 
       "is_outer": true
      }, 
      {
       "profile_curves": [
        {
         "center_point": {
          "y": 0.0482582, 
          "x": -0.09399432, 
          "z": 0.0
         }, 
         "radius": 0.001905, 
         "type": "Circle3D", 
         "curve": "KGRF", 
         "normal": {
          "y": 0.0, 
          "x": 0.0, 
          "z": 1.0
         }
        }
       ], 
       "is_outer": true
      }, 
      {
       "profile_curves": [
        {
         "center_point": {
          "y": 0.06573337, 
          "x": -0.09229132, 
          "z": 0.0
         }, 
         "radius": 0.0025, 
         "type": "Circle3D", 
         "curve": "KGVF", 
         "normal": {
          "y": 0.0, 
          "x": 0.0, 
          "z": 1.0
         }
        }
       ], 
       "is_outer": true
      }, 
      {
       "profile_curves": [
        {
         "center_point": {
          "y": 0.0283582, 
          "x": -0.10979832, 
          "z": 0.0
         }, 
         "radius": 0.00065, 
         "type": "Circle3D", 
         "curve": "KGhF", 
         "normal": {
          "y": 0.0, 
          "x": 0.0, 
          "z": 1.0
         }
        }
       ], 
       "is_outer": true
      }, 
      {
       "profile_curves": [
        {
         "center_point": {
          "y": 0.0283582, 
          "x": -0.10733832, 
          "z": 0.0
         }, 
         "radius": 0.00065, 
         "type": "Circle3D", 
         "curve": "KGFG", 
         "normal": {
          "y": 0.0, 
          "x": 0.0, 
          "z": 1.0
         }
        }
       ], 
       "is_outer": true
      }, 
      {
       "profile_curves": [
        {
         "center_point": {
          "y": 0.0283582, 
          "x": -0.10487832, 
          "z": 0.0
         }, 
         "radius": 0.00065, 
         "type": "Circle3D", 
         "curve": "KGJG", 
         "normal": {
          "y": 0.0, 
          "x": 0.0, 
          "z": 1.0
         }
        }
       ], 
       "is_outer": true
      }, 
      {
       "profile_curves": [
        {
         "center_point": {
          "y": 0.0283582, 
          "x": -0.10241832, 
          "z": 0.0
         }, 
         "radius": 0.00065, 
         "type": "Circle3D", 
         "curve": "KGNG", 
         "normal": {
          "y": 0.0, 
          "x": 0.0, 
          "z": 1.0
         }
        }
       ], 
       "is_outer": true
      }
     ], 
     "properties": {}
    }, 
    "KGKB": {
     "loops": [
      {
       "profile_curves": [
        {
         "center_point": {
          "y": 0.0283582, 
          "x": -0.04388912, 
          "z": 0.0
         }, 
         "radius": 0.00065, 
         "type": "Circle3D", 
         "curve": "KGlE", 
         "normal": {
          "y": 0.0, 
          "x": 0.0, 
          "z": 1.0
         }
        }
       ], 
       "is_outer": true
      }
     ], 
     "properties": {}
    }, 
    "KGOB": {
     "loops": [
      {
       "profile_curves": [
        {
         "center_point": {
          "y": 0.0283582, 
          "x": -0.04142912, 
          "z": 0.0
         }, 
         "radius": 0.00065, 
         "type": "Circle3D", 
         "curve": "KGpE", 
         "normal": {
          "y": 0.0, 
          "x": 0.0, 
          "z": 1.0
         }
        }
       ], 
       "is_outer": true
      }
     ], 
     "properties": {}
    }, 
    "KGuB": {
     "loops": [
      {
       "profile_curves": [
        {
         "center_point": {
          "y": 0.0283582, 
          "x": -0.10241832, 
          "z": 0.0
         }, 
         "radius": 0.00065, 
         "type": "Circle3D", 
         "curve": "KGNG", 
         "normal": {
          "y": 0.0, 
          "x": 0.0, 
          "z": 1.0
         }
        }
       ], 
       "is_outer": true
      }
     ], 
     "properties": {}
    }, 
    "KGWB": {
     "loops": [
      {
       "profile_curves": [
        {
         "start_point": {
          "y": 0.0363582, 
          "x": -0.10053686, 
          "z": 0.0
         }, 
         "type": "Line3D", 
         "curve": "KGxE", 
         "end_point": {
          "y": 0.0363582, 
          "x": -0.07003686, 
          "z": 0.0
         }
        }, 
        {
         "start_point": {
          "y": 0.0363582, 
          "x": -0.07003686, 
          "z": 0.0
         }, 
         "type": "Line3D", 
         "curve": "KG5E", 
         "end_point": {
          "y": 0.0138582, 
          "x": -0.07003686, 
          "z": 0.0
         }
        }, 
        {
         "start_point": {
          "y": 0.0138582, 
          "x": -0.07003686, 
          "z": 0.0
         }, 
         "type": "Line3D", 
         "curve": "KGxF", 
         "end_point": {
          "y": 0.0138582, 
          "x": -0.06628686, 
          "z": 0.0
         }
        }, 
        {
         "start_point": {
          "y": -0.0251418, 
          "x": -0.06628686, 
          "z": 0.0
         }, 
         "type": "Line3D", 
         "curve": "KGBF", 
         "end_point": {
          "y": 0.0138582, 
          "x": -0.06628686, 
          "z": 0.0
         }
        }, 
        {
         "start_point": {
          "y": -0.0251418, 
          "x": -0.07003686, 
          "z": 0.0
         }, 
         "type": "Line3D", 
         "curve": "KG5F", 
         "end_point": {
          "y": -0.0251418, 
          "x": -0.06628686, 
          "z": 0.0
         }
        }, 
        {
         "start_point": {
          "y": -0.0251418, 
          "x": -0.07003686, 
          "z": 0.0
         }, 
         "type": "Line3D", 
         "curve": "KG1E", 
         "end_point": {
          "y": -0.0521418, 
          "x": -0.07003686, 
          "z": 0.0
         }
        }, 
        {
         "start_point": {
          "y": -0.0521418, 
          "x": -0.07003686, 
          "z": 0.0
         }, 
         "type": "Line3D", 
         "curve": "KGBG", 
         "end_point": {
          "y": -0.0521418, 
          "x": -0.07703686, 
          "z": 0.0
         }
        }, 
        {
         "start_point": {
          "y": -0.0563918, 
          "x": -0.07703686, 
          "z": 0.0
         }, 
         "type": "Line3D", 
         "curve": "KG1F", 
         "end_point": {
          "y": -0.0521418, 
          "x": -0.07703686, 
          "z": 0.0
         }
        }, 
        {
         "start_point": {
          "y": -0.0563918, 
          "x": -0.10753686, 
          "z": 0.0
         }, 
         "type": "Line3D", 
         "curve": "KGJF", 
         "end_point": {
          "y": -0.0563918, 
          "x": -0.07703686, 
          "z": 0.0
         }
        }, 
        {
         "start_point": {
          "y": -0.0563918, 
          "x": -0.10753686, 
          "z": 0.0
         }, 
         "type": "Line3D", 
         "curve": "KGlF", 
         "end_point": {
          "y": -0.0521418, 
          "x": -0.10753686, 
          "z": 0.0
         }
        }, 
        {
         "start_point": {
          "y": -0.0521418, 
          "x": -0.11453686, 
          "z": 0.0
         }, 
         "type": "Line3D", 
         "curve": "KGdF", 
         "end_point": {
          "y": -0.0521418, 
          "x": -0.10753686, 
          "z": 0.0
         }
        }, 
        {
         "start_point": {
          "y": -0.0251418, 
          "x": -0.11453686, 
          "z": 0.0
         }, 
         "type": "Line3D", 
         "curve": "KGFF", 
         "end_point": {
          "y": -0.0521418, 
          "x": -0.11453686, 
          "z": 0.0
         }
        }, 
        {
         "start_point": {
          "y": -0.0251418, 
          "x": -0.11828686, 
          "z": 0.0
         }, 
         "type": "Line3D", 
         "curve": "KGpF", 
         "end_point": {
          "y": -0.0251418, 
          "x": -0.11453686, 
          "z": 0.0
         }
        }, 
        {
         "start_point": {
          "y": -0.0251418, 
          "x": -0.11828686, 
          "z": 0.0
         }, 
         "type": "Line3D", 
         "curve": "KG9E", 
         "end_point": {
          "y": 0.0138582, 
          "x": -0.11828686, 
          "z": 0.0
         }
        }, 
        {
         "start_point": {
          "y": 0.0138582, 
          "x": -0.11828686, 
          "z": 0.0
         }, 
         "type": "Line3D", 
         "curve": "KG9F", 
         "end_point": {
          "y": 0.0138582, 
          "x": -0.11453686, 
          "z": 0.0
         }
        }, 
        {
         "start_point": {
          "y": 0.0233582, 
          "x": -0.11453686, 
          "z": 0.0
         }, 
         "type": "Line3D", 
         "curve": "KGZF", 
         "end_point": {
          "y": 0.0138582, 
          "x": -0.11453686, 
          "z": 0.0
         }
        }, 
        {
         "start_point": {
          "y": 0.0233582, 
          "x": -0.10053686, 
          "z": 0.0
         }, 
         "type": "Line3D", 
         "curve": "KGNF", 
         "end_point": {
          "y": 0.0233582, 
          "x": -0.11453686, 
          "z": 0.0
         }
        }, 
        {
         "start_point": {
          "y": 0.0363582, 
          "x": -0.10053686, 
          "z": 0.0
         }, 
         "type": "Line3D", 
         "curve": "KGtF", 
         "end_point": {
          "y": 0.0233582, 
          "x": -0.10053686, 
          "z": 0.0
         }
        }
       ], 
       "is_outer": true
      }
     ], 
     "properties": {}
    }, 
    "JGq": {
     "loops": [
      {
       "profile_curves": [
        {
         "center_point": {
          "y": 0.0283582, 
          "x": 0.01710008, 
          "z": 0.0
         }, 
         "radius": 0.00065, 
         "type": "Circle3D", 
         "curve": "KGhC", 
         "normal": {
          "y": 0.0, 
          "x": 0.0, 
          "z": 1.0
         }
        }
       ], 
       "is_outer": true
      }
     ], 
     "properties": {}
    }, 
    "JG2": {
     "loops": [
      {
       "profile_curves": [
        {
         "center_point": {
          "y": 0.0283582, 
          "x": 0.02448008, 
          "z": 0.0
         }, 
         "radius": 0.00065, 
         "type": "Circle3D", 
         "curve": "KGND", 
         "normal": {
          "y": 0.0, 
          "x": 0.0, 
          "z": 1.0
         }
        }
       ], 
       "is_outer": true
      }
     ], 
     "properties": {}
    }, 
    "JGW": {
     "loops": [
      {
       "profile_curves": [
        {
         "center_point": {
          "y": 0.0482582, 
          "x": 0.09635328, 
          "z": 0.0
         }, 
         "radius": 0.001905, 
         "type": "Circle3D", 
         "curve": "KGFB", 
         "normal": {
          "y": 0.0, 
          "x": 0.0, 
          "z": 1.0
         }
        }
       ], 
       "is_outer": true
      }
     ], 
     "properties": {}
    }, 
    "JGu": {
     "loops": [
      {
       "profile_curves": [
        {
         "center_point": {
          "y": 0.0283582, 
          "x": 0.01956008, 
          "z": 0.0
         }, 
         "radius": 0.00065, 
         "type": "Circle3D", 
         "curve": "KGFD", 
         "normal": {
          "y": 0.0, 
          "x": 0.0, 
          "z": 1.0
         }
        }
       ], 
       "is_outer": true
      }
     ], 
     "properties": {}
    }, 
    "JG6": {
     "loops": [
      {
       "profile_curves": [
        {
         "start_point": {
          "y": 0.0363582, 
          "x": -0.03708766, 
          "z": 0.0
         }, 
         "type": "Line3D", 
         "curve": "KGRD", 
         "end_point": {
          "y": 0.0363582, 
          "x": -0.00658766, 
          "z": 0.0
         }
        }, 
        {
         "start_point": {
          "y": 0.0363582, 
          "x": -0.00658766, 
          "z": 0.0
         }, 
         "type": "Line3D", 
         "curve": "KGZD", 
         "end_point": {
          "y": 0.0138582, 
          "x": -0.00658766, 
          "z": 0.0
         }
        }, 
        {
         "start_point": {
          "y": 0.0138582, 
          "x": -0.00658766, 
          "z": 0.0
         }, 
         "type": "Line3D", 
         "curve": "KGRE", 
         "end_point": {
          "y": 0.0138582, 
          "x": -0.00283766, 
          "z": 0.0
         }
        }, 
        {
         "start_point": {
          "y": -0.0251418, 
          "x": -0.00283766, 
          "z": 0.0
         }, 
         "type": "Line3D", 
         "curve": "KGhD", 
         "end_point": {
          "y": 0.0138582, 
          "x": -0.00283766, 
          "z": 0.0
         }
        }, 
        {
         "start_point": {
          "y": -0.0251418, 
          "x": -0.00658766, 
          "z": 0.0
         }, 
         "type": "Line3D", 
         "curve": "KGZE", 
         "end_point": {
          "y": -0.0251418, 
          "x": -0.00283766, 
          "z": 0.0
         }
        }, 
        {
         "start_point": {
          "y": -0.0251418, 
          "x": -0.00658766, 
          "z": 0.0
         }, 
         "type": "Line3D", 
         "curve": "KGVD", 
         "end_point": {
          "y": -0.0521418, 
          "x": -0.00658766, 
          "z": 0.0
         }
        }, 
        {
         "start_point": {
          "y": -0.0521418, 
          "x": -0.00658766, 
          "z": 0.0
         }, 
         "type": "Line3D", 
         "curve": "KGhE", 
         "end_point": {
          "y": -0.0521418, 
          "x": -0.01358766, 
          "z": 0.0
         }
        }, 
        {
         "start_point": {
          "y": -0.0563918, 
          "x": -0.01358766, 
          "z": 0.0
         }, 
         "type": "Line3D", 
         "curve": "KGVE", 
         "end_point": {
          "y": -0.0521418, 
          "x": -0.01358766, 
          "z": 0.0
         }
        }, 
        {
         "start_point": {
          "y": -0.0563918, 
          "x": -0.04408766, 
          "z": 0.0
         }, 
         "type": "Line3D", 
         "curve": "KGpD", 
         "end_point": {
          "y": -0.0563918, 
          "x": -0.01358766, 
          "z": 0.0
         }
        }, 
        {
         "start_point": {
          "y": -0.0563918, 
          "x": -0.04408766, 
          "z": 0.0
         }, 
         "type": "Line3D", 
         "curve": "KGFE", 
         "end_point": {
          "y": -0.0521418, 
          "x": -0.04408766, 
          "z": 0.0
         }
        }, 
        {
         "start_point": {
          "y": -0.0521418, 
          "x": -0.05108766, 
          "z": 0.0
         }, 
         "type": "Line3D", 
         "curve": "KG9D", 
         "end_point": {
          "y": -0.0521418, 
          "x": -0.04408766, 
          "z": 0.0
         }
        }, 
        {
         "start_point": {
          "y": -0.0251418, 
          "x": -0.05108766, 
          "z": 0.0
         }, 
         "type": "Line3D", 
         "curve": "KGlD", 
         "end_point": {
          "y": -0.0521418, 
          "x": -0.05108766, 
          "z": 0.0
         }
        }, 
        {
         "start_point": {
          "y": -0.0251418, 
          "x": -0.05483766, 
          "z": 0.0
         }, 
         "type": "Line3D", 
         "curve": "KGJE", 
         "end_point": {
          "y": -0.0251418, 
          "x": -0.05108766, 
          "z": 0.0
         }
        }, 
        {
         "start_point": {
          "y": -0.0251418, 
          "x": -0.05483766, 
          "z": 0.0
         }, 
         "type": "Line3D", 
         "curve": "KGdD", 
         "end_point": {
          "y": 0.0138582, 
          "x": -0.05483766, 
          "z": 0.0
         }
        }, 
        {
         "start_point": {
          "y": 0.0138582, 
          "x": -0.05483766, 
          "z": 0.0
         }, 
         "type": "Line3D", 
         "curve": "KGdE", 
         "end_point": {
          "y": 0.0138582, 
          "x": -0.05108766, 
          "z": 0.0
         }
        }, 
        {
         "start_point": {
          "y": 0.0233582, 
          "x": -0.05108766, 
          "z": 0.0
         }, 
         "type": "Line3D", 
         "curve": "KG5D", 
         "end_point": {
          "y": 0.0138582, 
          "x": -0.05108766, 
          "z": 0.0
         }
        }, 
        {
         "start_point": {
          "y": 0.0233582, 
          "x": -0.03708766, 
          "z": 0.0
         }, 
         "type": "Line3D", 
         "curve": "KGtD", 
         "end_point": {
          "y": 0.0233582, 
          "x": -0.05108766, 
          "z": 0.0
         }
        }, 
        {
         "start_point": {
          "y": 0.0363582, 
          "x": -0.03708766, 
          "z": 0.0
         }, 
         "type": "Line3D", 
         "curve": "KGNE", 
         "end_point": {
          "y": 0.0233582, 
          "x": -0.03708766, 
          "z": 0.0
         }
        }
       ], 
       "is_outer": true
      }
     ], 
     "properties": {}
    }, 
    "KGaB": {
     "loops": [
      {
       "profile_curves": [
        {
         "center_point": {
          "y": 0.0482582, 
          "x": -0.09399432, 
          "z": 0.0
         }, 
         "radius": 0.001905, 
         "type": "Circle3D", 
         "curve": "KGRF", 
         "normal": {
          "y": 0.0, 
          "x": 0.0, 
          "z": 1.0
         }
        }
       ], 
       "is_outer": true
      }
     ], 
     "properties": {}
    }
   }, 
   "transform": {
    "origin": {
     "y": 0.0, 
     "x": 0.0, 
     "z": 0.0
    }, 
    "y_axis": {
     "y": 1.0, 
     "x": 0.0, 
     "z": 0.0
    }, 
    "x_axis": {
     "y": 0.0, 
     "x": 1.0, 
     "z": 0.0
    }, 
    "z_axis": {
     "y": 0.0, 
     "x": 0.0, 
     "z": 1.0
    }
   }
  }, 
  "FI4bYkDlNFuBAyB_0": {
   "extent_two": {
    "distance": {
     "role": "AgainstDistance", 
     "type": "ModelParameter", 
     "name": "none", 
     "value": 0.0
    }, 
    "type": "DistanceExtentDefinition", 
    "taper_angle": {
     "role": "Side2TaperAngle", 
     "type": "ModelParameter", 
     "name": "none", 
     "value": 0.0
    }
   }, 
   "name": "Top L2", 
   "extent_one": {
    "distance": {
     "role": "AlongDistance", 
     "type": "ModelParameter", 
     "name": "none", 
     "value": 0.003175
    }, 
    "type": "DistanceExtentDefinition", 
    "taper_angle": {
     "role": "TaperAngle", 
     "type": "ModelParameter", 
     "name": "none", 
     "value": 0.0
    }
   }, 
   "extent_type": "OneSideFeatureExtentType", 
   "operation": "NewBodyFeatureOperation", 
   "start_extent": {
    "type": "ProfilePlaneStartDefinition"
   }, 
   "type": "ExtrudeFeature", 
   "profiles": [
    {
     "profile": "KGyB", 
     "sketch": "FQPC0yPl8ZFWFSQ_0"
    }
   ]
  }, 
  "FqJdU3o8Z8upRF6_1": {
   "extent_two": {
    "distance": {
     "role": "AgainstDistance", 
     "type": "ModelParameter", 
     "name": "none", 
     "value": 0.0
    }, 
    "type": "DistanceExtentDefinition", 
    "taper_angle": {
     "role": "Side2TaperAngle", 
     "type": "ModelParameter", 
     "name": "none", 
     "value": 0.0
    }
   }, 
   "name": "Etching", 
   "extent_one": {
    "distance": {
     "role": "AlongDistance", 
     "type": "ModelParameter", 
     "name": "none", 
     "value": 5e-05
    }, 
    "type": "DistanceExtentDefinition", 
    "taper_angle": {
     "role": "TaperAngle", 
     "type": "ModelParameter", 
     "name": "none", 
     "value": 0.0
    }
   }, 
   "extent_type": "OneSideFeatureExtentType", 
   "operation": "CutFeatureOperation", 
   "start_extent": {
    "type": "ProfilePlaneStartDefinition"
   }, 
   "type": "ExtrudeFeature", 
   "profiles": [
    {
     "profile": "JGW", 
     "sketch": "FQPC0yPl8ZFWFSQ_0"
    }
   ]
  }
 }, 
 "properties": {
  "bounding_box": {
   "max_point": {
    "y": 0.08697020493656674, 
    "x": 0.13147580425856129, 
    "z": 0.003175
   }, 
   "type": "BoundingBox3D", 
   "min_point": {
    "y": -0.1370297950634333, 
    "x": -0.12652419574143872, 
    "z": 0.0
   }
  }
 }, 
 "sequence": [
  {
   "index": 0, 
   "type": "Sketch", 
   "entity": "FQPC0yPl8ZFWFSQ_0"
  }, 
  {
   "index": 1, 
   "type": "ExtrudeFeature", 
   "entity": "FI4bYkDlNFuBAyB_0"
  }, 
  {
   "index": 2, 
   "type": "ExtrudeFeature", 
   "entity": "FqJdU3o8Z8upRF6_1"
  }
 ]
}