{
 "entities": {
  "FEYDYuhX26mB4fJ_0": {
   "reference_plane": {}, 
   "type": "Sketch", 
   "name": "Sketch 1", 
   "profiles": {
    "JGC": {
     "loops": [
      {
       "profile_curves": [
        {
         "start_point": {
          "y": 0.00894803, 
          "x": 0.0, 
          "z": 0.0
         }, 
         "type": "Line3D", 
         "curve": "JGB", 
         "end_point": {
          "y": 0.00894803, 
          "x": -0.01345353, 
          "z": 0.0
         }
        }, 
        {
         "start_point": {
          "y": 0.00894803, 
          "x": -0.01345353, 
          "z": 0.0
         }, 
         "type": "Line3D", 
         "curve": "JGF", 
         "end_point": {
          "y": -0.01096557, 
          "x": -0.01345353, 
          "z": 0.0
         }
        }, 
        {
         "start_point": {
          "y": -0.01096557, 
          "x": -0.01345353, 
          "z": 0.0
         }, 
         "type": "Line3D", 
         "curve": "JGJ", 
         "end_point": {
          "y": -0.01096557, 
          "x": 0.0, 
          "z": 0.0
         }
        }, 
        {
         "start_point": {
          "y": -0.01096557, 
          "x": 0.0, 
          "z": 0.0
         }, 
         "type": "Line3D", 
         "curve": "JGV", 
         "end_point": {
          "y": -0.01096557, 
          "x": 0.01345353, 
          "z": 0.0
         }
        }, 
        {
         "start_point": {
          "y": 0.00894803, 
          "x": 0.01345353, 
          "z": 0.0
         }, 
         "type": "Line3D", 
         "curve": "JGR", 
         "end_point": {
          "y": -0.01096557, 
          "x": 0.01345353, 
          "z": 0.0
         }
        }, 
        {
         "start_point": {
          "y": 0.00894803, 
          "x": 0.0, 
          "z": 0.0
         }, 
         "type": "Line3D", 
         "curve": "JGN", 
         "end_point": {
          "y": 0.00894803, 
          "x": 0.01345353, 
          "z": 0.0
         }
        }
       ], 
       "is_outer": true
      }
     ], 
     "properties": {}
    }, 
    "JGG": {
     "loops": [
      {
       "profile_curves": [
        {
         "start_point": {
          "y": 0.00894803, 
          "x": 0.0, 
          "z": 0.0
         }, 
         "type": "Line3D", 
         "curve": "JGB", 
         "end_point": {
          "y": 0.00894803, 
          "x": -0.01345353, 
          "z": 0.0
         }
        }, 
        {
         "start_point": {
          "y": 0.00894803, 
          "x": -0.01345353, 
          "z": 0.0
         }, 
         "type": "Line3D", 
         "curve": "JGF", 
         "end_point": {
          "y": -0.01096557, 
          "x": -0.01345353, 
          "z": 0.0
         }
        }, 
        {
         "start_point": {
          "y": -0.01096557, 
          "x": -0.01345353, 
          "z": 0.0
         }, 
         "type": "Line3D", 
         "curve": "JGJ", 
         "end_point": {
          "y": -0.01096557, 
          "x": 0.0, 
          "z": 0.0
         }
        }, 
        {
         "start_point": {
          "y": -0.01096557, 
          "x": 0.0, 
          "z": 0.0
         }, 
         "type": "Line3D", 
         "curve": "JGV", 
         "end_point": {
          "y": -0.01096557, 
          "x": 0.01345353, 
          "z": 0.0
         }
        }, 
        {
         "start_point": {
          "y": 0.00894803, 
          "x": 0.01345353, 
          "z": 0.0
         }, 
         "type": "Line3D", 
         "curve": "JGR", 
         "end_point": {
          "y": -0.01096557, 
          "x": 0.01345353, 
          "z": 0.0
         }
        }, 
        {
         "start_point": {
          "y": 0.00894803, 
          "x": 0.0, 
          "z": 0.0
         }, 
         "type": "Line3D", 
         "curve": "JGN", 
         "end_point": {
          "y": 0.00894803, 
          "x": 0.01345353, 
          "z": 0.0
         }
        }
       ], 
       "is_outer": true
      }, 
      {
       "profile_curves": [
        {
         "start_point": {
          "y": 0.0152303, 
          "x": 0.0, 
          "z": 0.0
         }, 
         "type": "Line3D", 
         "curve": "JGZ", 
         "end_point": {
          "y": 0.0152303, 
          "x": -0.0144018, 
          "z": 0.0
         }
        }, 
        {
         "start_point": {
          "y": 0.0152303, 
          "x": -0.0144018, 
          "z": 0.0
         }, 
         "type": "Line3D", 
         "curve": "JGx", 
         "end_point": {
          "y": 0.02032723, 
          "x": -0.0144018, 
          "z": 0.0
         }
        }, 
        {
         "start_point": {
          "y": 0.02032723, 
          "x": -0.0144018, 
          "z": 0.0
         }, 
         "type": "Line3D", 
         "curve": "JG9", 
         "end_point": {
          "y": 0.02151257, 
          "x": -0.0268478, 
          "z": 0.0
         }
        }, 
        {
         "start_point": {
          "y": 0.0113187, 
          "x": -0.02376593, 
          "z": 0.0
         }, 
         "type": "Line3D", 
         "curve": "JG5", 
         "end_point": {
          "y": 0.02151257, 
          "x": -0.0268478, 
          "z": 0.0
         }
        }, 
        {
         "start_point": {
          "y": 0.0113187, 
          "x": -0.0176022, 
          "z": 0.0
         }, 
         "type": "Line3D", 
         "curve": "JG1", 
         "end_point": {
          "y": 0.0113187, 
          "x": -0.02376593, 
          "z": 0.0
         }
        }, 
        {
         "start_point": {
          "y": 0.0113187, 
          "x": -0.0176022, 
          "z": 0.0
         }, 
         "type": "Line3D", 
         "curve": "JGd", 
         "end_point": {
          "y": -0.00987956, 
          "x": -0.0176022, 
          "z": 0.0
         }
        }, 
        {
         "start_point": {
          "y": -0.00987956, 
          "x": -0.0176022, 
          "z": 0.0
         }, 
         "type": "Line3D", 
         "curve": "KGJB", 
         "end_point": {
          "y": -0.00804229, 
          "x": -0.02145286, 
          "z": 0.0
         }
        }, 
        {
         "start_point": {
          "y": -0.02019196, 
          "x": -0.02400132, 
          "z": 0.0
         }, 
         "type": "Line3D", 
         "curve": "KGNB", 
         "end_point": {
          "y": -0.00804229, 
          "x": -0.02145286, 
          "z": 0.0
         }
        }, 
        {
         "start_point": {
          "y": -0.02285896, 
          "x": -0.01374819, 
          "z": 0.0
         }, 
         "type": "Line3D", 
         "curve": "KGFB", 
         "end_point": {
          "y": -0.02019196, 
          "x": -0.02400132, 
          "z": 0.0
         }
        }, 
        {
         "start_point": {
          "y": -0.01523277, 
          "x": -0.01475572, 
          "z": 0.0
         }, 
         "type": "Line3D", 
         "curve": "KGBB", 
         "end_point": {
          "y": -0.02285896, 
          "x": -0.01374819, 
          "z": 0.0
         }
        }, 
        {
         "start_point": {
          "y": -0.01523277, 
          "x": -0.01475572, 
          "z": 0.0
         }, 
         "type": "Line3D", 
         "curve": "JGh", 
         "end_point": {
          "y": -0.01523277, 
          "x": 0.0, 
          "z": 0.0
         }
        }, 
        {
         "start_point": {
          "y": -0.01523277, 
          "x": 0.0, 
          "z": 0.0
         }, 
         "type": "Line3D", 
         "curve": "JGt", 
         "end_point": {
          "y": -0.01523277, 
          "x": 0.01465385, 
          "z": 0.0
         }
        }, 
        {
         "start_point": {
          "y": -0.01523277, 
          "x": 0.01465385, 
          "z": 0.0
         }, 
         "type": "Line3D", 
         "curve": "KGlB", 
         "end_point": {
          "y": -0.01895388, 
          "x": 0.01465385, 
          "z": 0.0
         }
        }, 
        {
         "start_point": {
          "y": -0.01895388, 
          "x": 0.01465385, 
          "z": 0.0
         }, 
         "type": "Line3D", 
         "curve": "KGpB", 
         "end_point": {
          "y": -0.02205506, 
          "x": 0.01951517, 
          "z": 0.0
         }
        }, 
        {
         "start_point": {
          "y": -0.02205506, 
          "x": 0.01951517, 
          "z": 0.0
         }, 
         "type": "Line3D", 
         "curve": "KGtB", 
         "end_point": {
          "y": -0.01451164, 
          "x": 0.02177819, 
          "z": 0.0
         }
        }, 
        {
         "start_point": {
          "y": -0.01342204, 
          "x": 0.02085622, 
          "z": 0.0
         }, 
         "type": "Line3D", 
         "curve": "KGxB", 
         "end_point": {
          "y": -0.01451164, 
          "x": 0.02177819, 
          "z": 0.0
         }
        }, 
        {
         "start_point": {
          "y": -0.01342204, 
          "x": 0.0176022, 
          "z": 0.0
         }, 
         "type": "Line3D", 
         "curve": "KGhB", 
         "end_point": {
          "y": -0.01342204, 
          "x": 0.02085622, 
          "z": 0.0
         }
        }, 
        {
         "start_point": {
          "y": 0.01163886, 
          "x": 0.0176022, 
          "z": 0.0
         }, 
         "type": "Line3D", 
         "curve": "JGp", 
         "end_point": {
          "y": -0.01342204, 
          "x": 0.0176022, 
          "z": 0.0
         }
        }, 
        {
         "start_point": {
          "y": 0.01163886, 
          "x": 0.0176022, 
          "z": 0.0
         }, 
         "type": "Line3D", 
         "curve": "KGVB", 
         "end_point": {
          "y": 0.01163886, 
          "x": 0.02135911, 
          "z": 0.0
         }
        }, 
        {
         "start_point": {
          "y": 0.01163886, 
          "x": 0.02135911, 
          "z": 0.0
         }, 
         "type": "Line3D", 
         "curve": "KGZB", 
         "end_point": {
          "y": 0.02261872, 
          "x": 0.01767122, 
          "z": 0.0
         }
        }, 
        {
         "start_point": {
          "y": 0.02043951, 
          "x": 0.01348043, 
          "z": 0.0
         }, 
         "type": "Line3D", 
         "curve": "KGdB", 
         "end_point": {
          "y": 0.02261872, 
          "x": 0.01767122, 
          "z": 0.0
         }
        }, 
        {
         "start_point": {
          "y": 0.0152303, 
          "x": 0.01348043, 
          "z": 0.0
         }, 
         "type": "Line3D", 
         "curve": "KGRB", 
         "end_point": {
          "y": 0.02043951, 
          "x": 0.01348043, 
          "z": 0.0
         }
        }, 
        {
         "start_point": {
          "y": 0.0152303, 
          "x": 0.0, 
          "z": 0.0
         }, 
         "type": "Line3D", 
         "curve": "JGl", 
         "end_point": {
          "y": 0.0152303, 
          "x": 0.01348043, 
          "z": 0.0
         }
        }
       ], 
       "is_outer": true
      }
     ], 
     "properties": {}
    }
   }, 
   "transform": {
    "origin": {
     "y": 0.0, 
     "x": 0.0, 
     "z": 0.0
    }, 
    "y_axis": {
     "y": 0.0, 
     "x": -0.0, 
     "z": 1.0
    }, 
    "x_axis": {
     "y": 0.0, 
     "x": 1.0, 
     "z": 0.0
    }, 
    "z_axis": {
     "y": -1.0, 
     "x": 0.0, 
     "z": 0.0
    }
   }
  }, 
  "FZEAgWLg6CMIoiN_0": {
   "extent_two": {
    "distance": {
     "role": "AgainstDistance", 
     "type": "ModelParameter", 
     "name": "none", 
     "value": 0.0
    }, 
    "type": "DistanceExtentDefinition", 
    "taper_angle": {
     "role": "Side2TaperAngle", 
     "type": "ModelParameter", 
     "name": "none", 
     "value": 0.0
    }
   }, 
   "name": "Extrude 1", 
   "extent_one": {
    "distance": {
     "role": "AlongDistance", 
     "type": "ModelParameter", 
     "name": "none", 
     "value": 0.007
    }, 
    "type": "DistanceExtentDefinition", 
    "taper_angle": {
     "role": "TaperAngle", 
     "type": "ModelParameter", 
     "name": "none", 
     "value": 0.0
    }
   }, 
   "extent_type": "OneSideFeatureExtentType", 
   "operation": "NewBodyFeatureOperation", 
   "start_extent": {
    "type": "ProfilePlaneStartDefinition"
   }, 
   "type": "ExtrudeFeature", 
   "profiles": [
    {
     "profile": "JGG", 
     "sketch": "FEYDYuhX26mB4fJ_0"
    }
   ]
  }
 }, 
 "properties": {
  "bounding_box": {
   "max_point": {
    "y": 0.0, 
    "x": 0.02177819050848484, 
    "z": 0.022618724033236504
   }, 
   "type": "BoundingBox3D", 
   "min_point": {
    "y": -0.007, 
    "x": -0.026847800239920616, 
    "z": -0.022858958691358566
   }
  }
 }, 
 "sequence": [
  {
   "index": 0, 
   "type": "Sketch", 
   "entity": "FEYDYuhX26mB4fJ_0"
  }, 
  {
   "index": 1, 
   "type": "ExtrudeFeature", 
   "entity": "FZEAgWLg6CMIoiN_0"
  }
 ]
}